bepusdt/__init__.py
bepusdt/client.py
bepusdt/exceptions.py
bepusdt/models.py
bepusdt/retry.py
bepusdt/signature.py
bepusdt-0.3.1.dist-info/licenses/LICENSE
bepusdt-0.3.1.dist-info/METADATA
bepusdt-0.3.1.dist-info/WHEEL
bepusdt-0.3.1.dist-info/top_level.txt
bepusdt-0.3.1.dist-info/RECORD
