Metadata-Version: 2.4
Name: bepusdt
Version: 0.3.1
Summary: BEpusdt 支付网关 Python SDK - 支持 USDT/TRX/USDC 多链支付
Home-page: https://github.com/luoyanglang/bepusdt-python-sdk
Author: luoyanglang
Author-email: luoyanglang <luoyanglang@users.noreply.github.com>
License: MIT
Project-URL: Homepage, https://github.com/luoyanglang/bepusdt-python-sdk
Project-URL: Documentation, https://github.com/luoyanglang/bepusdt-python-sdk#readme
Project-URL: Repository, https://github.com/luoyanglang/bepusdt-python-sdk
Project-URL: Issues, https://github.com/luoyanglang/bepusdt-python-sdk/issues
Keywords: bepusdt,payment,usdt,trx,cryptocurrency,blockchain
Classifier: Development Status :: 4 - Beta
Classifier: Intended Audience :: Developers
Classifier: Topic :: Software Development :: Libraries :: Python Modules
Classifier: License :: OSI Approved :: MIT License
Classifier: Programming Language :: Python :: 3
Classifier: Programming Language :: Python :: 3.7
Classifier: Programming Language :: Python :: 3.8
Classifier: Programming Language :: Python :: 3.9
Classifier: Programming Language :: Python :: 3.10
Classifier: Programming Language :: Python :: 3.11
Classifier: Programming Language :: Python :: 3.12
Requires-Python: >=3.7
License-File: LICENSE
Requires-Dist: requests>=2.25.0
Provides-Extra: dev
Requires-Dist: pytest>=7.0.0; extra == "dev"
Requires-Dist: pytest-cov>=3.0.0; extra == "dev"
Requires-Dist: black>=22.0.0; extra == "dev"
Requires-Dist: flake8>=4.0.0; extra == "dev"
Requires-Dist: mypy>=0.950; extra == "dev"
Dynamic: author
Dynamic: home-page
Dynamic: license-file
Dynamic: requires-python
